{"cameraMode":{"drawMode":0,"name":"Shaded","section":"Shading Mode"},"sceneLighting":false,"audioPlay":false,"sceneViewState":{"showFog":true,"showMaterialUpdate":false,"showSkybox":false,"showFlares":true,"showImageEffects":true,"showParticleSystems":true},"in2DMode":false,"pivot":{"x":646.2780151367188,"y":261.3609924316406,"z":4.9679999351501469},"rotation":{"x":-0.17324815690517426,"y":0.04489041864871979,"z":-0.007905148901045323,"w":-0.9838231801986694},"size":0.1499999314546585,"orthographic":false}